docs/source/conf.py
m3_tox_docker-5.1.0.dist-info/licenses/LICENSE
tox_docker/__init__.py
tox_docker/config.py
tox_docker/plugin.py
tox_docker/tests/__init__.py
tox_docker/tests/test_containers.py
tox_docker/tests/test_env_vars.py
tox_docker/tests/test_gateway.py
tox_docker/tests/test_healthcheck.py
tox_docker/tests/test_images.py
tox_docker/tests/test_links.py
tox_docker/tests/test_ports.py
tox_docker/tests/test_volumes.py
tox_docker/tests/util.py
m3_tox_docker-5.1.0.dist-info/METADATA
m3_tox_docker-5.1.0.dist-info/WHEEL
m3_tox_docker-5.1.0.dist-info/entry_points.txt
m3_tox_docker-5.1.0.dist-info/top_level.txt
m3_tox_docker-5.1.0.dist-info/RECORD
