Metadata-Version: 2.4
Name: m3-tox-docker
Version: 5.1.0
Summary: Manage lifecycle of docker containers during Tox test runs
Maintainer-email: Dan Crosta <dcrosta@late.am>
License-Expression: BSD-4-Clause
Project-URL: Homepage, https://github.com/tox-dev/tox-docker
Classifier: Development Status :: 5 - Production/Stable
Classifier: Environment :: Plugins
Classifier: Intended Audience :: Developers
Classifier: Programming Language :: Python :: 3.8
Classifier: Programming Language :: Python :: 3.9
Classifier: Programming Language :: Python :: 3.10
Classifier: Programming Language :: Python :: 3.11
Classifier: Topic :: Software Development :: Testing
Requires-Python: >=3.8
License-File: LICENSE
Requires-Dist: docker<8.0,>=4.0
Requires-Dist: tox<5.0,>=4.0.0
Dynamic: license-file
